pikka_bird_collector/__init__.py
pikka_bird_collector/app.py
pikka_bird_collector/collector.py
pikka_bird_collector/config.py
pikka_bird_collector/sender.py
pikka_bird_collector/collectors/__init__.py
pikka_bird_collector/collectors/base.py
pikka_bird_collector/collectors/base_port_command.py
pikka_bird_collector/collectors/mongodb.py
pikka_bird_collector/collectors/mysql.py
pikka_bird_collector/collectors/postgresql.py
pikka_bird_collector/collectors/rabbitmq.py
pikka_bird_collector/collectors/redis.py
pikka_bird_collector/collectors/system.py
pikka_bird_collector/parsers/__init__.py
pikka_bird_collector/parsers/base.py
pikka_bird_collector/parsers/erlang.py
pikka_bird_collector/parsers/redis.py
pikka_bird_collector/parsers/table.py
pikka_bird_collector-0.2.0.data/scripts/pikka-bird-collector
pikka_bird_collector-0.2.0.dist-info/DESCRIPTION.rst
pikka_bird_collector-0.2.0.dist-info/METADATA
pikka_bird_collector-0.2.0.dist-info/metadata.json
pikka_bird_collector-0.2.0.dist-info/RECORD
pikka_bird_collector-0.2.0.dist-info/top_level.txt
pikka_bird_collector-0.2.0.dist-info/WHEEL
