Metadata-Version: 2.0
Name: pikka-bird-collector
Version: 0.2.0
Summary: Pikka Bird ops monitoring tool Collector component.
Home-page: https://github.com/tiredpixel/pikka-bird-collector-py
Author: tiredpixel
Author-email: tp@tiredpixel.com
License: MIT
Keywords: ops monitoring sysadmin
Platform: UNKNOWN
Classifier: Development Status :: 3 - Alpha
Classifier: Intended Audience :: System Administrators
Classifier: License :: OSI Approved :: MIT License
Classifier: Programming Language :: Python :: 2
Classifier: Programming Language :: Python :: 2.7
Classifier: Programming Language :: Python :: 3
Classifier: Programming Language :: Python :: 3.2
Classifier: Programming Language :: Python :: 3.3
Classifier: Programming Language :: Python :: 3.4
Requires-Dist: msgpack-python
Requires-Dist: psutil
Requires-Dist: PyYAML
Requires-Dist: requests
